Workbook

Sheet ColumnSummary
A1: カラム名 | B1: ユニーク数 | C1: 説明
A2: ProjectID | B2: =ROUND(SUMPRODUCT(1/COUNTIF(Sheet1!A2:A721,Sheet1!A2:A721)),0) -> 20 | C2: プロジェクト識別子
A3: asof | B3: =ROUND(SUMPRODUCT(1/COUNTIF(Sheet1!B2:B721,Sheet1!B2:B721)),0) -> 36 | C3: 基準日（シリアル値）
A4: StartDate | B4: =ROUND(SUMPRODUCT(1/COUNTIF(Sheet1!C2:C721,Sheet1!C2:C721)),0) -> 20 | C4: プロジェクト開始日
A5: CompletionDate | B5: =ROUND(SUMPRODUCT(1/COUNTIF(Sheet1!D2:D721,Sheet1!D2:D721)),0) -> 20 | C5: プロジェクト完了予定日
A6: TotalSales | B6: =ROUND(SUMPRODUCT(1/COUNTIF(Sheet1!E2:E721,Sheet1!E2:E721)),0) -> 695 | C6: 総売上高
A7: AccumSales | B7: =ROUND(SUMPRODUCT(1/COUNTIF(Sheet1!F2:F721,Sheet1!F2:F721)),0) -> 676 | C7: 累計売上高
A8: RemainingSales | B8: =ROUND(SUMPRODUCT(1/COUNTIF(Sheet1!G2:G721,Sheet1!G2:G721)),0) -> 454 | C8: 残売上高
A9: TotalEstimatedCost | B9: =ROUND(SUMPRODUCT(1/COUNTIF(Sheet1!H2:H721,Sheet1!H2:H721)),0) -> 686 | C9: 総見積コスト
A10: AccumCost | B10: =ROUND(SUMPRODUCT(1/COUNTIF(Sheet1!I2:I721,Sheet1!I2:I721)),0) -> 675 | C10: 累計コスト
A11: AccumProfit | B11: =ROUND(SUMPRODUCT(1/COUNTIF(Sheet1!J2:J721,Sheet1!J2:J721)),0) -> 697 | C11: 累計利益
A12: Profit | B12: =ROUND(SUMPRODUCT(1/COUNTIF(Sheet1!K2:K721,Sheet1!K2:K721)),0) -> 701 | C12: 利益
A13: Margin | B13: =ROUND(SUMPRODUCT(1/COUNTIF(Sheet1!L2:L721,Sheet1!L2:L721)),0) -> 711 | C13: 利益率（%）
A14: AmendRecognizedProfit | B14: =ROUND(SUMPRODUCT(1/COUNTIF(Sheet1!M2:M721,Sheet1!M2:M721)),0) -> 197 | C14: 修正認識利益
A15: ContractAmount | B15: =ROUND(SUMPRODUCT(1/COUNTIF(Sheet1!N2:N721,Sheet1!N2:N721)),0) -> 694 | C15: 契約金額
A16: UnsignedContractAmount | B16: =ROUND(SUMPRODUCT(1/COUNTIF(Sheet1!O2:O721,Sheet1!O2:O721)),0) -> 611 | C16: 未署名契約金額
A17: ElapsedTime | B17: =ROUND(SUMPRODUCT(1/COUNTIF(Sheet1!P2:P721,Sheet1!P2:P721)),0) -> 547 | C17: 経過時間（日数）
A18: CostProgress | B18: =ROUND(SUMPRODUCT(1/COUNTIF(Sheet1!Q2:Q721,Sheet1!Q2:Q721)),0) -> 505 | C18: コスト進捗率（%）
A19: Customer | B19: =ROUND(SUMPRODUCT(1/COUNTIF(Sheet1!R2:R721,Sheet1!R2:R721)),0) -> 5 | C19: 顧客名
A20: SalesGroup | B20: =ROUND(SUMPRODUCT(1/COUNTIF(Sheet1!S2:S721,Sheet1!S2:S721)),0) -> 3 | C20: 営業グループ
A21: DevGroup | B21: =ROUND(SUMPRODUCT(1/COUNTIF(Sheet1!T2:T721,Sheet1!T2:T721)),0) -> 4 | C21: 開発グループ
A22: JV | B22: =ROUND(SUMPRODUCT(1/COUNTIF(Sheet1!U2:U721,Sheet1!U2:U721)),0) -> 3 | C22: ジョイントベンチャー
A23: ProjectType | B23: =ROUND(SUMPRODUCT(1/COUNTIF(Sheet1!V2:V721,Sheet1!V2:V721)),0) -> 3 | C23: プロジェクトタイプ

Sheet Sheet1
A1: ProjectID | B1: asof | C1: StartDate | D1: CompletionDate | E1: TotalSales | F1: AccumSales | G1: RemainingSales | H1: TotalEstimatedCost | I1: AccumCost | J1: AccumProfit | K1: Profit | L1: Margin | M1: AmendRecognizedProfit | N1: ContractAmount | O1: UnsignedContractAmount | P1: ElapsedTime | Q1: CostProgress | R1: Customer | S1: SalesGroup | T1: DevGroup | U1: JV | V1: ProjectType
A2: 10001 | B2: 44681 | C2: 45066 | D2: 45764 | E2: 10060000 | F2: 10060000 | G2: 0 | H2: 24040000 | I2: 24040000 | J2: -13980000 | K2: -13980000 | L2: -138.97 | M2: -610000 | N2: 94450000 | O2: 12730000 | P2: -385 | Q2: 9 | R2: CustomerD | S2: Sales_Osaka | T2: Dev_Team3 | U2: None | V2: TypeC
A3: 10001 | B3: 44712 | C3: 45066 | D3: 45764 | E3: 52780000 | F3: 52780000 | G3: 0 | H3: 38250000 | I3: 22200000 | J3: 30580000 | K3: 14530000 | L3: 27.53 | M3: -440000 | N3: 92400000 | O3: 3560000 | P3: -354 | Q3: 21.2 | R3: CustomerC | S3: Sales_Tokyo | T3: Dev_Team3 | U3: None | V3: TypeB
A4: 10001 | B4: 44742 | C4: 45066 | D4: 45764 | E4: 29810000 | F4: 29810000 | G4: 0 | H4: 38240000 | I4: 30100000 | J4: -290000 | K4: -8430000 | L4: -28.28 | M4: 730000 | N4: 65090000 | O4: 1610000 | P4: -324 | Q4: 43.9 | R4: CustomerC | S4: Sales_Nagoya | T4: Dev_Team4 | U4: JV_A | V4: TypeB
A5: 10001 | B5: 44773 | C5: 45066 | D5: 45764 | E5: 44180000 | F5: 12780000 | G5: 31400000 | H5: 9500000 | I5: 9500000 | J5: 3280000 | K5: 34680000 | L5: 78.5 | M5: -940000 | N5: 92720000 | O5: 11320000 | P5: -293 | Q5: 77.8 | R5: CustomerA | S5: Sales_Osaka | T5: Dev_Team3 | U5: None | V5: TypeB
A6: 10001 | B6: 44804 | C6: 45066 | D6: 45764 | E6: 65150000 | F6: 26040000 | G6: 39110000 | H6: 35390000 | I6: 17750000 | J6: 8290000 | K6: 29760000 | L6: 45.68 | M6: 560000 | N6: 66360000 | O6: 16340000 | P6: -262 | Q6: 85.1 | R6: CustomerC | S6: Sales_Tokyo | T6: Dev_Team2 | U6: None | V6: TypeC
A7: 10001 | B7: 44834 | C7: 45066 | D7: 45764 | E7: 41660000 | F7: 32110000 | G7: 9550000 | H7: 38410000 | I7: 5260000 | J7: 26850000 | K7: 3250000 | L7: 7.8 | M7: -90000 | N7: 21380000 | O7: 15190000 | P7: -232 | Q7: 62.5 | R7: CustomerA | S7: Sales_Tokyo | T7: Dev_Team2 | U7: None | V7: TypeB
A8: 10001 | B8: 44865 | C8: 45066 | D8: 45764 | E8: 20000000 | F8: 20000000 | G8: 0 | H8: 21780000 | I8: 21780000 | J8: -1780000 | K8: -1780000 | L8: -8.9 | M8: -840000 | N8: 22840000 | O8: 11440000 | P8: -201 | Q8: 38.8 | R8: CustomerC | S8: Sales_Tokyo | T8: Dev_Team2 | U8: None | V8: TypeB
A9: 10001 | B9: 44895 | C9: 45066 | D9: 45764 | E9: 31930000 | F9: 31930000 | G9: 0 | H9: 58780000 | I9: 18560000 | J9: 13370000 | K9: -26850000 | L9: -84.09 | M9: 810000 | N9: 71350000 | O9: 19780000 | P9: -171 | Q9: 14.4 | R9: CustomerC | S9: Sales_Tokyo | T9: Dev_Team4 | U9: None | V9: TypeA
A10: 10001 | B10: 44926 | C10: 45066 | D10: 45764 | E10: 70130000 | F10: 32440000 | G10: 37690000 | H10: 8970000 | I10: 8970000 | J10: 23470000 | K10: 61160000 | L10: 87.21 | M10: -620000 | N10: 93070000 | O10: 19900000 | P10: -140 | Q10: 88.2 | R10: CustomerB | S10: Sales_Osaka | T10: Dev_Team2 | U10: JV_A | V10: TypeC
A11: 10001 | B11: 44957 | C11: 45066 | D11: 45764 | E11: 47590000 | F11: 14100000 | G11: 33490000 | H11: 60650000 | I11: 8220000 | J11: 5880000 | K11: -13060000 | L11: -27.44 | M11: 490000 | N11: 23560000 | O11: 6430000 | P11: -109 | Q11: 87.4 | R11: CustomerD | S11: Sales_Nagoya | T11: Dev_Team3 | U11: JV_A | V11: TypeB
A12: 10001 | B12: 44985 | C12: 45066 | D12: 45764 | E12: 80940000 | F12: 8520000 | G12: 72420000 | H12: 39160000 | I12: 39160000 | J12: -30640000 | K12: 41780000 | L12: 51.62 | M12: -140000 | N12: 89640000 | O12: 3440000 | P12: -81 | Q12: 33.9 | R12: CustomerA | S12: Sales_Nagoya | T12: Dev_Team4 | U12: JV_A | V12: TypeC
A13: 10001 | B13: 45016 | C13: 45066 | D13: 45764 | E13: 19260000 | F13: 19260000 | G13: 0 | H13: 60650000 | I13: 55440000 | J13: -36180000 | K13: -41390000 | L13: -214.9 | M13: 340000 | N13: 50520000 | O13: 7440000 | P13: -50 | Q13: 51.3 | R13: CustomerB | S13: Sales_Nagoya | T13: Dev_Team3 | U13: None | V13: TypeC
... A721: 10020 | B721: 45747 | C721: 44677 | D721: 45319 | E721: 29750000 | F721: 29750000 | G721: 0 | H721: 41990000 | I721: 41990000 | J721: -12240000 | K721: -12240000 | L721: -41.14 | M721: -940000 | N721: 47870000 | O721: 19180000 | P721: 1070 | Q721: 66.8 | R721: CustomerC | S721: Sales_Tokyo | T721: Dev_Team4 | U721: JV_B | V721: TypeB
